{
  "taskId": "squad-zsnus",
  "title": "add docs linke (squad.tools) and star this repo to /squad/readme.md",
  "summary": [
    "Updated README.md with documentation link for squad.tools",
    "Added star button/reference to repository in README"
  ],
  "outcome": "completed",
  "duration": "10 minutes",
  "agent": "CoolSpring",
  "keyChanges": [
    "/squad/README.md"
  ],
  "quality": {
    "tests": "none",
    "build": "clean"
  },
  "suggestedTasks": [
    {
      "type": "chore",
      "title": "Create comprehensive repository documentation for squad.tools",
      "description": "Develop a detailed documentation structure for the squad.tools project. This should include installation instructions, usage guidelines, configuration details, and API references. The documentation will help new contributors and users understand the project quickly and reduce onboarding friction.",
      "priority": 2,
      "reason": "Current documentation appears minimal and needs expansion"
    }
  ],
  "crossAgentIntel": {
    "files": [
      "/squad/README.md"
    ],
    "patterns": [
      "Adding external project references",
      "Including repository engagement elements"
    ]
  },
  "riskLevel": "low",
  "generatedAt": "2026-01-30T10:38:52.788Z"
}